j5basic/API.py
j5basic/CleanXHTML.py
j5basic/CleanupIterator.py
j5basic/Colours.py
j5basic/Converters.py
j5basic/Decorators.py
j5basic/DesignPatterns.py
j5basic/DictUtils.py
j5basic/EndlessIterator.py
j5basic/EnumClass.py
j5basic/Errors.py
j5basic/Formatters.py
j5basic/ImportModuleDef.py
j5basic/InfiniteClasses.py
j5basic/Module.py
j5basic/ObjTracker.py
j5basic/OrderedSet.py
j5basic/PushBack.py
j5basic/Ranges.py
j5basic/SemiSortedSet.py
j5basic/SetupUtils.py
j5basic/Singleton.py
j5basic/TimeCache.py
j5basic/TimeUtils.py
j5basic/TimedLock.py
j5basic/Timer.py
j5basic/TzInfo.py
j5basic/Uid.py
j5basic/Units.py
j5basic/WithContextSkip.py
j5basic/__init__.py
j5basic/cStringIOWrapper.py
j5basic/test_API.py
j5basic/test_CleanXHTML.py
j5basic/test_CleanupIterator.py
j5basic/test_Colours.py
j5basic/test_Converters.py
j5basic/test_Decorators.py
j5basic/test_DesignPatterns.py
j5basic/test_DictUtils.py
j5basic/test_EndlessIterator.py
j5basic/test_EnumClass.py
j5basic/test_Errors.py
j5basic/test_Formatters.py
j5basic/test_ImportModuleDef.py
j5basic/test_InfiniteClasses.py
j5basic/test_Module.py
j5basic/test_ObjTracker.py
j5basic/test_OrderedSet.py
j5basic/test_PushBack.py
j5basic/test_Ranges.py
j5basic/test_SemiSortedSet.py
j5basic/test_Singleton.py
j5basic/test_TimeCache.py
j5basic/test_TimeUtils.py
j5basic/test_TimedLock.py
j5basic/test_Timer.py
j5basic/test_Uid.py
j5basic/test_Units.py
j5basic/test_WithContextSkip.py
j5basic/test_WithContextSkip_cpython.py
j5basic/test_cStringIOWrapper.py
j5basic-1.5.dist-info/LICENSE
j5basic-1.5.dist-info/METADATA
j5basic-1.5.dist-info/WHEEL
j5basic-1.5.dist-info/top_level.txt
j5basic-1.5.dist-info/RECORD
