Metadata-Version: 2.1
Name: j5basic
Version: 1.5
Summary: A collection of utility methods and classes.
Home-page: http://www.sjsoft.com/
Author: St James Software
Author-email: support@sjsoft.com
License: Apache License, Version 2.0
Platform: UNKNOWN
Classifier: Development Status :: 5 - Production/Stable
Classifier: License :: OSI Approved :: Apache Software License
Classifier: Environment :: Web Environment
Classifier: Intended Audience :: Developers
Classifier: Operating System :: OS Independent
Classifier: Programming Language :: Python
Classifier: Programming Language :: Python :: 2 :: Only
Classifier: Topic :: Software Development :: Libraries :: Python Modules
Requires-Dist: future
Provides-Extra: cleanxhtml
Requires-Dist: cssutils ; extra == 'cleanxhtml'
Requires-Dist: lxml ; extra == 'cleanxhtml'
Provides-Extra: colours
Requires-Dist: numpy ; extra == 'colours'
Provides-Extra: tests
Requires-Dist: j5test ; extra == 'tests'
Provides-Extra: time-related
Requires-Dist: pytz ; extra == 'time-related'
Requires-Dist: virtualtime ; extra == 'time-related'
